Portenta/__init__.py
Portenta/GPIO/__init__.py
Portenta/GPIO/event_producer.py
Portenta/GPIO/gpio.py
Portenta/GPIO/portenta_gpio_map.py
RPi/__init__.py
RPi/GPIO/__init__.py
Portenta.GPIO-0.1.2.dist-info/LICENSE.txt
Portenta.GPIO-0.1.2.dist-info/METADATA
Portenta.GPIO-0.1.2.dist-info/WHEEL
Portenta.GPIO-0.1.2.dist-info/top_level.txt
Portenta.GPIO-0.1.2.dist-info/RECORD
