Metadata-Version: 2.1
Name: Portenta.GPIO
Version: 0.1.2
Summary: A module to control Portenta GPIO channels
Home-page: https://github.com/SuMere/portenta-gpio
Author: Riccardo Mereu
Author-email: Riccardo Mereu <r.mereu@arduino.cc>
License: MIT
Project-URL: Homepage, https://github.com/SuMere/portenta-gpio
Project-URL: Bug Tracker, https://github.com/SuMere/portenta-gpio/issues
Keywords: Portenta GPIO
Classifier: Operating System :: POSIX :: Linux
Classifier: License :: OSI Approved :: MIT License
Classifier: Intended Audience :: Developers
Classifier: Programming Language :: Python :: 3
Classifier: Topic :: Software Development
Classifier: Topic :: System :: Hardware
Requires-Python: >=3.7
License-File: LICENSE.txt
